LICENSE
nonebot_plugin_bwiki_navigator/__init__.py
nonebot_plugin_bwiki_navigator/config.py
nonebot_plugin_bwiki_navigator/handler.py
nonebot_plugin_bwiki_navigator/parser.py
nonebot_plugin_bwiki_navigator-0.2.1.dist-info/LICENSE
nonebot_plugin_bwiki_navigator-0.2.1.dist-info/METADATA
nonebot_plugin_bwiki_navigator-0.2.1.dist-info/WHEEL
nonebot_plugin_bwiki_navigator-0.2.1.dist-info/RECORD
