Metadata-Version: 2.1
Name: nonebot-plugin-bwiki-navigator
Version: 0.2.1
Summary: A nonebot2 plugin version of bwiki official bot
Home-page: https://github.com/XZhouQD/nonebot-plugin-bwiki-navigator
License: AGPL v3
Author: XZhouQD
Author-email: X.Zhou.QD@hotmail.com
Requires-Python: >=3.8,<4.0
Classifier: License :: Other/Proprietary License
Classifier: Programming Language :: Python :: 3
Classifier: Programming Language :: Python :: 3.8
Classifier: Programming Language :: Python :: 3.9
Classifier: Programming Language :: Python :: 3.10
Classifier: Programming Language :: Python :: 3.11
Requires-Dist: httpx[http2] (>=0.20.0,<1.0.0)
Requires-Dist: nonebot-adapter-onebot (>=2.0.0-beta.1,<3.0.0)
Requires-Dist: nonebot2 (>=2.0.0,<3.0.0)
Project-URL: Repository, https://github.com/XZhouQD/nonebot-plugin-bwiki-navigator
